{"cameraMode":{"drawMode":0,"name":"Shaded","section":"Shading Mode"},"sceneLighting":true,"audioPlay":false,"sceneViewState":{"m_AlwaysRefresh":false,"showFog":true,"showSkybox":true,"showFlares":true,"showImageEffects":true,"showParticleSystems":true,"showVisualEffectGraphs":true,"m_FxEnabled":true},"in2DMode":false,"pivot":{"x":78.0323486328125,"y":5.033581733703613,"z":-180.19898986816407},"rotation":{"x":-0.26186269521713259,"y":0.2679430842399597,"z":-0.07657407224178314,"w":-0.9241078495979309},"size":8.682777404785157,"orthographic":false}